README.txt
TODO.txt
setup.py
docs/HISTORY.txt
docs/INSTALL.txt
docs/LICENSE.GPL
docs/LICENSE.txt
sixfeetup/__init__.py
sixfeetup.workflow.chained.egg-info/PKG-INFO
sixfeetup.workflow.chained.egg-info/SOURCES.txt
sixfeetup.workflow.chained.egg-info/dependency_links.txt
sixfeetup.workflow.chained.egg-info/entry_points.txt
sixfeetup.workflow.chained.egg-info/namespace_packages.txt
sixfeetup.workflow.chained.egg-info/not-zip-safe
sixfeetup.workflow.chained.egg-info/requires.txt
sixfeetup.workflow.chained.egg-info/top_level.txt
sixfeetup/workflow/__init__.py
sixfeetup/workflow/chained/__init__.py
sixfeetup/workflow/chained/configure.zcml
sixfeetup/workflow/chained/overrides.zcml
sixfeetup/workflow/chained/tests.py
sixfeetup/workflow/chained/browser/__init__.py
sixfeetup/workflow/chained/browser/contenthistory.py
sixfeetup/workflow/chained/browser/foldercontents.pt
sixfeetup/workflow/chained/browser/foldercontents.py
sixfeetup/workflow/chained/browser/menu.py
sixfeetup/workflow/chained/browser/table.pt
sixfeetup/workflow/chained/template_overrides/plone.app.contentmenu.contentmenu.pt
sixfeetup/workflow/chained/template_overrides/plone.app.layout.viewlets.content_history.pt