Metadata-Version: 1.1
Name: sixfeetup.workflow.chained
Version: 1.9
Summary: Override the state menu to show all states in the workflow chain
Home-page: http://www.sixfeetup.com
Author: Six Feet Up, Inc.
Author-email: info@sixfeetup.com
License: GPL
Keywords: plone workflow
Platform: UNKNOWN
Classifier: Framework :: Plone
Classifier: Programming Language :: Python
Classifier: Topic :: Software Development :: Libraries :: Python Modules
